nonebot_plugin_uniconf/__init__.py
nonebot_plugin_uniconf/manager.py
nonebot_plugin_uniconf/types.py
nonebot_plugin_uniconf-0.1.3.dist-info/licenses/LICENSE
nonebot_plugin_uniconf-0.1.3.dist-info/METADATA
nonebot_plugin_uniconf-0.1.3.dist-info/WHEEL
nonebot_plugin_uniconf-0.1.3.dist-info/top_level.txt
nonebot_plugin_uniconf-0.1.3.dist-info/RECORD
