Metadata-Version: 2.4
Name: nonebot-plugin-uniconf
Version: 0.1.3
Summary: File config manager for nonebot2
Project-URL: Homepage, https://github.com/LiteSuggarDEV/nonebot_plugin_uniconf
Project-URL: Source, https://github.com/LiteSuggarDEV/nonebot_plugin_uniconf
Project-URL: Issue Tracker, https://github.com/LiteSuggarDEV/nonebot_plugin_uniconf/issues
Requires-Python: >=3.10
License-File: LICENSE
Requires-Dist: aiofiles>=25.1.0
Requires-Dist: nonebot-plugin-localstore>=0.7.4
Requires-Dist: nonebot2>=2.4.4
Requires-Dist: tomli>=2.3.0
Requires-Dist: tomli-w>=1.2.0
Requires-Dist: watchfiles>=1.1.1
Dynamic: license-file
